derive/__init__.py
derive/config.py
derive/integrations/__init__.py
derive/integrations/aws_xray.py
derive/integrations/console.py
derive/integrations/fluentbit.py
derive/integrations/kubernetes.py
derive/integrations/requests.py
derive/log/__init__.py
derive/log/formatter.py
derive/log/record.py
derive/log/types.py
derive/metrics/__init__.py
derive/metrics/collector.py
derive/metrics/context_manger.py
derive/metrics/exporter.py
derive/metrics/manager.py
derive/metrics/metric/__init__.py
derive/metrics/metric/base.py
derive/metrics/metric/label.py
derive/trace/__init__.py
derive/trace/base.py
derive-0.2.2.dist-info/WHEEL
derive-0.2.2.dist-info/METADATA
derive-0.2.2.dist-info/RECORD
