Metadata-Version: 2.1
Name: derive
Version: 0.2.2
Summary: The Python Observability Toolkit
Home-page: https://github.com/DeBankDeFi/derive
License: MIT
Keywords: python,observability,opentelemetry
Author: DeBankDeFi
Author-email: sre@debank.com
Requires-Python: >=3.7.2,<4.0
Classifier: Development Status :: 4 - Beta
Classifier: License :: OSI Approved :: MIT License
Classifier: Programming Language :: Python :: 3
Classifier: Programming Language :: Python :: 3.10
Classifier: Programming Language :: Python :: 3.7
Classifier: Programming Language :: Python :: 3.8
Classifier: Programming Language :: Python :: 3.9
Classifier: Topic :: Software Development
Classifier: Topic :: Software Development :: Libraries :: Python Modules
Provides-Extra: otlp-aws-xray
Provides-Extra: requests
Requires-Dist: configalchemy (>=0.5.5,<0.6.0)
Requires-Dist: opentelemetry-api (>=1.11.1,<2.0.0)
Requires-Dist: opentelemetry-exporter-otlp (>=1.11,<2.0); extra == "otlp-aws-xray"
Requires-Dist: opentelemetry-instrumentation-requests (==0.30b1); extra == "requests"
Requires-Dist: opentelemetry-propagator-aws-xray (>=1.0,<2.0); extra == "otlp-aws-xray"
Requires-Dist: opentelemetry-sdk (>=1.11.1,<2.0.0)
Requires-Dist: opentelemetry-sdk-extension-aws (>=2.0,<3.0); extra == "otlp-aws-xray"
Requires-Dist: protobuf (>=3.10,<4.0); extra == "otlp-aws-xray"
Project-URL: Documentation, https://github.com/DeBankDeFi/derive
Project-URL: Repository, https://github.com/DeBankDeFi/derive
